{
  "main": {
    "id": "cb735ac45307a59e",
    "type": "split",
    "children": [
      {
        "id": "ed2ef7cb9d30b8fe",
        "type": "tabs",
        "children": [
          {
            "id": "fc19ef5b592e845c",
            "type": "leaf",
            "state": {
              "type": "empty",
              "state": {},
              "icon": "lucide-file",
              "title": "New tab"
            }
          }
        ]
      }
    ],
    "direction": "vertical"
  },
  "left": {
    "id": "ec66ea44089646e7",
    "type": "split",
    "children": [
      {
        "id": "25d489dadab5a15b",
        "type": "tabs",
        "children": [
          {
            "id": "6aa82632e350c8a6",
            "type": "leaf",
            "state": {
              "type": "file-explorer",
              "state": {
                "sortOrder": "alphabetical",
                "autoReveal": false
              },
              "icon": "lucide-folder-closed",
              "title": "Files"
            }
          },
          {
            "id": "dce326bfaae6fb52",
            "type": "leaf",
            "state": {
              "type": "search",
              "state": {
                "query": "",
                "matchingCase": false,
                "explainSearch": false,
                "collapseAll": false,
                "extraContext": false,
                "sortOrder": "alphabetical"
              },
              "icon": "lucide-search",
              "title": "Search"
            }
          },
          {
            "id": "97ce489a27eb67a7",
            "type": "leaf",
            "state": {
              "type": "bookmarks",
              "state": {},
              "icon": "lucide-bookmark",
              "title": "Bookmarks"
            }
          }
        ]
      }
    ],
    "direction": "horizontal",
    "width": 300
  },
  "right": {
    "id": "afde6217884e96e3",
    "type": "split",
    "children": [
      {
        "id": "0b7f85e27fd25f80",
        "type": "tabs",
        "children": [
          {
            "id": "0fd15d14dc67a6e1",
            "type": "leaf",
            "state": {
              "type": "backlink",
              "state": {
                "collapseAll": false,
                "extraContext": false,
                "sortOrder": "alphabetical",
                "showSearch": false,
                "searchQuery": "",
                "backlinkCollapsed": false,
                "unlinkedCollapsed": true
              },
              "icon": "links-coming-in",
              "title": "Backlinks"
            }
          },
          {
            "id": "7e0a534cdc909eda",
            "type": "leaf",
            "state": {
              "type": "outgoing-link",
              "state": {
                "linksCollapsed": false,
                "unlinkedCollapsed": true
              },
              "icon": "links-going-out",
              "title": "Outgoing links"
            }
          },
          {
            "id": "dba516c0221cb304",
            "type": "leaf",
            "state": {
              "type": "tag",
              "state": {
                "sortOrder": "frequency",
                "useHierarchy": true,
                "showSearch": false,
                "searchQuery": ""
              },
              "icon": "lucide-tags",
              "title": "Tags"
            }
          },
          {
            "id": "a1170de54da1e261",
            "type": "leaf",
            "state": {
              "type": "all-properties",
              "state": {
                "sortOrder": "frequency",
                "showSearch": false,
                "searchQuery": ""
              },
              "icon": "lucide-archive",
              "title": "All properties"
            }
          },
          {
            "id": "12cc40fc92080760",
            "type": "leaf",
            "state": {
              "type": "outline",
              "state": {
                "followCursor": false,
                "showSearch": false,
                "searchQuery": ""
              },
              "icon": "lucide-list",
              "title": "Outline"
            }
          }
        ]
      }
    ],
    "direction": "horizontal",
    "width": 300,
    "collapsed": true
  },
  "left-ribbon": {
    "hiddenItems": {
      "switcher:Open quick switcher": false,
      "graph:Open graph view": false,
      "canvas:Create new canvas": false,
      "daily-notes:Open today's daily note": false,
      "templates:Insert template": false,
      "command-palette:Open command palette": false,
      "bases:Create new base": false
    }
  },
  "active": "fc19ef5b592e845c",
  "lastOpenFiles": []
}